{"community_id":1145,"name":"Ufhusen","wikipedia_link":"https://de.wikipedia.org/wiki/Ufhusen","wikipedia_images":[{"url":"https://upload.wikimedia.org/wikipedia/commons/3/36/Ufhsuen_209.jpg"},{"url":"https://upload.wikimedia.org/wikipedia/commons/a/a9/Warmisbach_apud_Lochmueli_en_Ufhusen_219.jpg"},{"url":"https://upload.wikimedia.org/wikipedia/commons/d/d1/Ruefswil_Ufhusen_elkavlago_226.jpg"},{"url":"https://upload.wikimedia.org/wikipedia/commons/e/ea/Ufhusen_LU.png"}],"births":[{"year":1981,"births":9},{"year":1982,"births":9},{"year":1983,"births":9},{"year":1984,"births":14},{"year":1985,"births":12},{"year":1986,"births":11},{"year":1987,"births":15},{"year":1988,"births":12},{"year":1989,"births":9},{"year":1990,"births":11},{"year":1991,"births":14},{"year":1992,"births":11},{"year":1993,"births":12},{"year":1994,"births":10},{"year":1995,"births":8},{"year":1996,"births":17},{"year":1997,"births":13},{"year":1998,"births":6},{"year":1999,"births":8},{"year":2000,"births":15},{"year":2001,"births":12},{"year":2002,"births":13},{"year":2003,"births":8},{"year":2004,"births":6},{"year":2005,"births":13},{"year":2006,"births":5},{"year":2007,"births":7},{"year":2008,"births":8},{"year":2009,"births":9},{"year":2010,"births":18},{"year":2011,"births":7},{"year":2012,"births":7},{"year":2013,"births":8},{"year":2014,"births":8}],"deaths":[{"year":1981,"deaths":8},{"year":1982,"deaths":12},{"year":1983,"deaths":6},{"year":1984,"deaths":5},{"year":1985,"deaths":1},{"year":1986,"deaths":6},{"year":1987,"deaths":4},{"year":1988,"deaths":11},{"year":1989,"deaths":7},{"year":1990,"deaths":9},{"year":1991,"deaths":11},{"year":1992,"deaths":7},{"year":1993,"deaths":8},{"year":1994,"deaths":6},{"year":1995,"deaths":6},{"year":1996,"deaths":6},{"year":1997,"deaths":8},{"year":1998,"deaths":11},{"year":1999,"deaths":4},{"year":2000,"deaths":9},{"year":2001,"deaths":3},{"year":2002,"deaths":6},{"year":2003,"deaths":5},{"year":2004,"deaths":6},{"year":2005,"deaths":8},{"year":2006,"deaths":4},{"year":2007,"deaths":12},{"year":2008,"deaths":7},{"year":2009,"deaths":6},{"year":2010,"deaths":13},{"year":2011,"deaths":6},{"year":2012,"deaths":7},{"year":2013,"deaths":6},{"year":2014,"deaths":5}],"residential_population":[{"year":1981,"population":743},{"year":1982,"population":744},{"year":1983,"population":756},{"year":1984,"population":774},{"year":1985,"population":782},{"year":1986,"population":782},{"year":1987,"population":783},{"year":1988,"population":784},{"year":1989,"population":777},{"year":1990,"population":763},{"year":1991,"population":815},{"year":1992,"population":813},{"year":1993,"population":798},{"year":1994,"population":796},{"year":1995,"population":810},{"year":1996,"population":823},{"year":1997,"population":826},{"year":1998,"population":818},{"year":1999,"population":807},{"year":2000,"population":805},{"year":2001,"population":809},{"year":2002,"population":813},{"year":2003,"population":817},{"year":2004,"population":831},{"year":2005,"population":841},{"year":2006,"population":834},{"year":2007,"population":835},{"year":2008,"population":846},{"year":2009,"population":857},{"year":2010,"population":855},{"year":2011,"population":848},{"year":2012,"population":848},{"year":2013,"population":855},{"year":2014,"population":869}],"language_areas":[{"year":2000,"language":"Deutsches Sprachgebiet"}],"housing_estate_share":[{"year":2004,"share":5.4693877551}],"commuter_balance":[{"year":2000,"commuters":-158,"balance_per_100_workers":-29.2}],"cinemas":[{"year":2014,"cinemas":0}],"population_by_age_groups":[{"community_id":1145,"year":2014,"sex":"male","population_5_9_years":24,"population_10_14_years":27,"population_15_19_years":27,"population_20_24_years":36,"population_25_29_years":27,"population_30_34_years":28,"population_35_39_years":23,"population_40_44_years":36,"population_45_49_years":47,"population_50_54_years":37,"population_55_59_years":25,"population_60_64_years":23,"population_65_69_years":20,"population_70_74_years":17,"population_75_79_years":10,"population_80_84_years":16,"population_85_89_years":5,"population_90_94_years":2,"population_95_99_years":0,"population_100_years_or_older":0},{"community_id":1145,"year":2014,"sex":"female","population_5_9_years":21,"population_10_14_years":30,"population_15_19_years":29,"population_20_24_years":29,"population_25_29_years":25,"population_30_34_years":23,"population_35_39_years":29,"population_40_44_years":32,"population_45_49_years":32,"population_50_54_years":34,"population_55_59_years":22,"population_60_64_years":16,"population_65_69_years":19,"population_70_74_years":23,"population_75_79_years":11,"population_80_84_years":11,"population_85_89_years":5,"population_90_94_years":2,"population_95_99_years":0,"population_100_years_or_older":0}],"immigration":[{"year":1981,"immigration":1},{"year":1982,"immigration":1},{"year":1983,"immigration":2},{"year":1984,"immigration":1},{"year":1985,"immigration":1},{"year":1986,"immigration":0},{"year":1987,"immigration":1},{"year":1988,"immigration":0},{"year":1989,"immigration":4},{"year":1990,"immigration":2},{"year":1991,"immigration":0},{"year":1992,"immigration":3},{"year":1993,"immigration":2},{"year":1994,"immigration":8},{"year":1995,"immigration":1},{"year":1996,"immigration":0},{"year":1997,"immigration":0},{"year":1998,"immigration":5},{"year":1999,"immigration":0},{"year":2000,"immigration":0},{"year":2001,"immigration":1},{"year":2002,"immigration":1},{"year":2003,"immigration":1},{"year":2004,"immigration":2},{"year":2005,"immigration":1},{"year":2006,"immigration":1},{"year":2007,"immigration":5},{"year":2008,"immigration":8},{"year":2009,"immigration":3},{"year":2010,"immigration":3},{"year":2011,"immigration":7},{"year":2012,"immigration":5},{"year":2013,"immigration":8},{"year":2014,"immigration":14}],"emigration":[{"year":1981,"emigration":2},{"year":1982,"emigration":1},{"year":1983,"emigration":3},{"year":1984,"emigration":2},{"year":1985,"emigration":0},{"year":1986,"emigration":2},{"year":1987,"emigration":0},{"year":1988,"emigration":0},{"year":1989,"emigration":3},{"year":1990,"emigration":2},{"year":1991,"emigration":1},{"year":1992,"emigration":0},{"year":1993,"emigration":0},{"year":1994,"emigration":1},{"year":1995,"emigration":0},{"year":1996,"emigration":1},{"year":1997,"emigration":1},{"year":1998,"emigration":0},{"year":1999,"emigration":0},{"year":2000,"emigration":0},{"year":2001,"emigration":0},{"year":2002,"emigration":0},{"year":2003,"emigration":0},{"year":2004,"emigration":0},{"year":2005,"emigration":1},{"year":2006,"emigration":3},{"year":2007,"emigration":1},{"year":2008,"emigration":0},{"year":2009,"emigration":2},{"year":2010,"emigration":1},{"year":2011,"emigration":1},{"year":2012,"emigration":2},{"year":2013,"emigration":2},{"year":2014,"emigration":4}],"immigration_from_same_canton":[{"year":1981,"immigration":7},{"year":1982,"immigration":19},{"year":1983,"immigration":30},{"year":1984,"immigration":12},{"year":1985,"immigration":9},{"year":1986,"immigration":15},{"year":1987,"immigration":5},{"year":1988,"immigration":9},{"year":1989,"immigration":16},{"year":1990,"immigration":15},{"year":1991,"immigration":21},{"year":1992,"immigration":16},{"year":1993,"immigration":13},{"year":1994,"immigration":17},{"year":1995,"immigration":9},{"year":1996,"immigration":14},{"year":1997,"immigration":21},{"year":1998,"immigration":19},{"year":1999,"immigration":16},{"year":2000,"immigration":20},{"year":2001,"immigration":20},{"year":2002,"immigration":13},{"year":2003,"immigration":17},{"year":2004,"immigration":37},{"year":2005,"immigration":10},{"year":2006,"immigration":12},{"year":2007,"immigration":16},{"year":2008,"immigration":29},{"year":2009,"immigration":17},{"year":2010,"immigration":22},{"year":2011,"immigration":14},{"year":2012,"immigration":16},{"year":2013,"immigration":28},{"year":2014,"immigration":25}],"immigration_from_other_canton":[{"year":1981,"immigration":20},{"year":1982,"immigration":7},{"year":1983,"immigration":23},{"year":1984,"immigration":17},{"year":1985,"immigration":24},{"year":1986,"immigration":17},{"year":1987,"immigration":27},{"year":1988,"immigration":19},{"year":1989,"immigration":8},{"year":1990,"immigration":10},{"year":1991,"immigration":10},{"year":1992,"immigration":5},{"year":1993,"immigration":13},{"year":1994,"immigration":11},{"year":1995,"immigration":33},{"year":1996,"immigration":18},{"year":1997,"immigration":11},{"year":1998,"immigration":4},{"year":1999,"immigration":7},{"year":2000,"immigration":8},{"year":2001,"immigration":9},{"year":2002,"immigration":11},{"year":2003,"immigration":11},{"year":2004,"immigration":7},{"year":2005,"immigration":15},{"year":2006,"immigration":10},{"year":2007,"immigration":25},{"year":2008,"immigration":18},{"year":2009,"immigration":23},{"year":2010,"immigration":9},{"year":2011,"immigration":8},{"year":2012,"immigration":12},{"year":2013,"immigration":17},{"year":2014,"immigration":24}],"emigration_from_same_canton":[{"year":1981,"emigration":9},{"year":1982,"emigration":4},{"year":1983,"emigration":11},{"year":1984,"emigration":10},{"year":1985,"emigration":19},{"year":1986,"emigration":22},{"year":1987,"emigration":21},{"year":1988,"emigration":30},{"year":1989,"emigration":15},{"year":1990,"emigration":26},{"year":1991,"emigration":11},{"year":1992,"emigration":22},{"year":1993,"emigration":28},{"year":1994,"emigration":26},{"year":1995,"emigration":10},{"year":1996,"emigration":18},{"year":1997,"emigration":26},{"year":1998,"emigration":17},{"year":1999,"emigration":28},{"year":2000,"emigration":18},{"year":2001,"emigration":29},{"year":2002,"emigration":27},{"year":2003,"emigration":16},{"year":2004,"emigration":20},{"year":2005,"emigration":19},{"year":2006,"emigration":19},{"year":2007,"emigration":15},{"year":2008,"emigration":21},{"year":2009,"emigration":21},{"year":2010,"emigration":37},{"year":2011,"emigration":16},{"year":2012,"emigration":17},{"year":2013,"emigration":23},{"year":2014,"emigration":34}],"emigration_from_other_canton":[{"year":1981,"emigration":18},{"year":1982,"emigration":17},{"year":1983,"emigration":20},{"year":1984,"emigration":17},{"year":1985,"emigration":19},{"year":1986,"emigration":20},{"year":1987,"emigration":14},{"year":1988,"emigration":8},{"year":1989,"emigration":17},{"year":1990,"emigration":24},{"year":1991,"emigration":13},{"year":1992,"emigration":20},{"year":1993,"emigration":23},{"year":1994,"emigration":8},{"year":1995,"emigration":8},{"year":1996,"emigration":16},{"year":1997,"emigration":11},{"year":1998,"emigration":21},{"year":1999,"emigration":8},{"year":2000,"emigration":10},{"year":2001,"emigration":6},{"year":2002,"emigration":6},{"year":2003,"emigration":11},{"year":2004,"emigration":7},{"year":2005,"emigration":15},{"year":2006,"emigration":18},{"year":2007,"emigration":16},{"year":2008,"emigration":22},{"year":2009,"emigration":11},{"year":2010,"emigration":16},{"year":2011,"emigration":15},{"year":2012,"emigration":10},{"year":2013,"emigration":13},{"year":2014,"emigration":13}],"birth_surplus":[{"year":1981,"surplus":1},{"year":1982,"surplus":-3},{"year":1983,"surplus":3},{"year":1984,"surplus":9},{"year":1985,"surplus":11},{"year":1986,"surplus":5},{"year":1987,"surplus":11},{"year":1988,"surplus":1},{"year":1989,"surplus":2},{"year":1990,"surplus":2},{"year":1991,"surplus":3},{"year":1992,"surplus":4},{"year":1993,"surplus":4},{"year":1994,"surplus":4},{"year":1995,"surplus":2},{"year":1996,"surplus":11},{"year":1997,"surplus":5},{"year":1998,"surplus":-5},{"year":1999,"surplus":4},{"year":2000,"surplus":6},{"year":2001,"surplus":9},{"year":2002,"surplus":7},{"year":2003,"surplus":3},{"year":2004,"surplus":0},{"year":2005,"surplus":5},{"year":2006,"surplus":1},{"year":2007,"surplus":-5},{"year":2008,"surplus":1},{"year":2009,"surplus":3},{"year":2010,"surplus":5},{"year":2011,"surplus":1},{"year":2012,"surplus":0},{"year":2013,"surplus":2},{"year":2014,"surplus":3}],"migration_balance":[{"year":1981,"balance":-1},{"year":1982,"balance":0},{"year":1983,"balance":-1},{"year":1984,"balance":-1},{"year":1985,"balance":1},{"year":1986,"balance":-2},{"year":1987,"balance":1},{"year":1988,"balance":0},{"year":1989,"balance":1},{"year":1990,"balance":0},{"year":1991,"balance":-1},{"year":1992,"balance":3},{"year":1993,"balance":2},{"year":1994,"balance":7},{"year":1995,"balance":1},{"year":1996,"balance":-1},{"year":1997,"balance":-1},{"year":1998,"balance":5},{"year":1999,"balance":0},{"year":2000,"balance":0},{"year":2001,"balance":1},{"year":2002,"balance":1},{"year":2003,"balance":1},{"year":2004,"balance":2},{"year":2005,"balance":0},{"year":2006,"balance":-2},{"year":2007,"balance":4},{"year":2008,"balance":8},{"year":2009,"balance":1},{"year":2010,"balance":2},{"year":2011,"balance":6},{"year":2012,"balance":3},{"year":2013,"balance":6},{"year":2014,"balance":10}],"new_citizenships":[{"year":1981,"citizenships":0},{"year":1982,"citizenships":0},{"year":1983,"citizenships":0},{"year":1984,"citizenships":0},{"year":1985,"citizenships":0},{"year":1986,"citizenships":0},{"year":1987,"citizenships":0},{"year":1988,"citizenships":0},{"year":1989,"citizenships":0},{"year":1990,"citizenships":0},{"year":1991,"citizenships":0},{"year":1992,"citizenships":0},{"year":1993,"citizenships":0},{"year":1994,"citizenships":0},{"year":1995,"citizenships":0},{"year":1996,"citizenships":0},{"year":1997,"citizenships":0},{"year":1998,"citizenships":0},{"year":1999,"citizenships":0},{"year":2000,"citizenships":0},{"year":2001,"citizenships":0},{"year":2002,"citizenships":0},{"year":2003,"citizenships":0},{"year":2004,"citizenships":0},{"year":2005,"citizenships":0},{"year":2006,"citizenships":0},{"year":2007,"citizenships":0},{"year":2008,"citizenships":0},{"year":2009,"citizenships":0},{"year":2010,"citizenships":0},{"year":2011,"citizenships":0},{"year":2012,"citizenships":0},{"year":2013,"citizenships":0},{"year":2014,"citizenships":0}],"commute_distance":null,"population_birth_place_switzerland":[{"year":1981,"people":737},{"year":1982,"people":742},{"year":1983,"people":756},{"year":1984,"people":772},{"year":1985,"people":781},{"year":1986,"people":781},{"year":1987,"people":782},{"year":1988,"people":784},{"year":1989,"people":774},{"year":1990,"people":760},{"year":1991,"people":814},{"year":1992,"people":812},{"year":1993,"people":794},{"year":1994,"people":789},{"year":1995,"people":803},{"year":1996,"people":817},{"year":1997,"people":822},{"year":1998,"people":815},{"year":1999,"people":802},{"year":2000,"people":797},{"year":2001,"people":800},{"year":2002,"people":804},{"year":2003,"people":806},{"year":2004,"people":818},{"year":2005,"people":826},{"year":2006,"people":819},{"year":2007,"people":816},{"year":2008,"people":821},{"year":2009,"people":830},{"year":2010,"people":828},{"year":2011,"people":819},{"year":2012,"people":814},{"year":2013,"people":819},{"year":2014,"people":832}],"population_birth_place_abroad":[{"year":1981,"people":6},{"year":1982,"people":2},{"year":1983,"people":0},{"year":1984,"people":2},{"year":1985,"people":1},{"year":1986,"people":1},{"year":1987,"people":1},{"year":1988,"people":0},{"year":1989,"people":3},{"year":1990,"people":3},{"year":1991,"people":1},{"year":1992,"people":1},{"year":1993,"people":4},{"year":1994,"people":7},{"year":1995,"people":7},{"year":1996,"people":6},{"year":1997,"people":4},{"year":1998,"people":3},{"year":1999,"people":5},{"year":2000,"people":8},{"year":2001,"people":9},{"year":2002,"people":9},{"year":2003,"people":11},{"year":2004,"people":13},{"year":2005,"people":15},{"year":2006,"people":15},{"year":2007,"people":19},{"year":2008,"people":25},{"year":2009,"people":27},{"year":2010,"people":27},{"year":2011,"people":30},{"year":2012,"people":34},{"year":2013,"people":36},{"year":2014,"people":38}],"workplaces_by_sector":[{"year":2013,"sector":1,"workplaces":62,"workers":152},{"year":2013,"sector":2,"workplaces":19,"workers":72},{"year":2013,"sector":3,"workplaces":31,"workers":108}],"workplaces_by_size":[{"year":2013,"workplace_size":"micro","workplaces":110,"workers":295},{"year":2013,"workplace_size":"small","workplaces":2,"workers":37},{"year":2013,"workplace_size":"medium","workplaces":0,"workers":0},{"year":2013,"workplace_size":"big","workplaces":0,"workers":0}],"political_parties":[{"year":1975,"party":"Other","voters":4},{"year":1975,"party":"CVP/PDC","voters":261},{"year":1975,"party":"SVP/UDC","voters":0},{"year":1975,"party":"FDP/PLR (PRD)","voters":85},{"year":1975,"party":"GLP/PVL","voters":0},{"year":1975,"party":"SP/PS","voters":2},{"year":1975,"party":"GPS/PES","voters":0},{"year":1975,"party":"BDP/PBD","voters":0},{"year":1979,"party":"BDP/PBD","voters":0},{"year":1979,"party":"CVP/PDC","voters":206},{"year":1979,"party":"GPS/PES","voters":0},{"year":1979,"party":"Other","voters":3},{"year":1979,"party":"SP/PS","voters":3},{"year":1979,"party":"FDP/PLR (PRD)","voters":92},{"year":1979,"party":"GLP/PVL","voters":0},{"year":1979,"party":"SVP/UDC","voters":0},{"year":1983,"party":"SP/PS","voters":3},{"year":1983,"party":"SVP/UDC","voters":0},{"year":1983,"party":"CVP/PDC","voters":244},{"year":1983,"party":"FDP/PLR (PRD)","voters":90},{"year":1983,"party":"GLP/PVL","voters":0},{"year":1983,"party":"Other","voters":6},{"year":1983,"party":"BDP/PBD","voters":0},{"year":1983,"party":"GPS/PES","voters":0},{"year":1987,"party":"Other","voters":8},{"year":1987,"party":"CVP/PDC","voters":238},{"year":1987,"party":"BDP/PBD","voters":0},{"year":1987,"party":"SVP/UDC","voters":0},{"year":1987,"party":"FDP/PLR (PRD)","voters":98},{"year":1987,"party":"SP/PS","voters":1},{"year":1987,"party":"GLP/PVL","voters":0},{"year":1987,"party":"GPS/PES","voters":0},{"year":1991,"party":"GLP/PVL","voters":0},{"year":1991,"party":"FDP/PLR (PRD)","voters":66},{"year":1991,"party":"Other","voters":5},{"year":1991,"party":"SVP/UDC","voters":0},{"year":1991,"party":"BDP/PBD","voters":0},{"year":1991,"party":"SP/PS","voters":3},{"year":1991,"party":"GPS/PES","voters":10},{"year":1991,"party":"CVP/PDC","voters":238},{"year":1995,"party":"Other","voters":1},{"year":1995,"party":"GPS/PES","voters":3},{"year":1995,"party":"BDP/PBD","voters":0},{"year":1995,"party":"SP/PS","voters":5},{"year":1995,"party":"SVP/UDC","voters":51},{"year":1995,"party":"GLP/PVL","voters":0},{"year":1995,"party":"FDP/PLR (PRD)","voters":66},{"year":1995,"party":"CVP/PDC","voters":173},{"year":1999,"party":"Other","voters":8},{"year":1999,"party":"GPS/PES","voters":4},{"year":1999,"party":"SP/PS","voters":2},{"year":1999,"party":"GLP/PVL","voters":0},{"year":1999,"party":"CVP/PDC","voters":157},{"year":1999,"party":"BDP/PBD","voters":0},{"year":1999,"party":"SVP/UDC","voters":79},{"year":1999,"party":"FDP/PLR (PRD)","voters":63},{"year":2003,"party":"SP/PS","voters":3},{"year":2003,"party":"GLP/PVL","voters":0},{"year":2003,"party":"CVP/PDC","voters":156},{"year":2003,"party":"FDP/PLR (PRD)","voters":51},{"year":2003,"party":"BDP/PBD","voters":0},{"year":2003,"party":"Other","voters":6},{"year":2003,"party":"GPS/PES","voters":8},{"year":2003,"party":"SVP/UDC","voters":65},{"year":2007,"party":"FDP/PLR (PRD)","voters":46},{"year":2007,"party":"Other","voters":3},{"year":2007,"party":"SP/PS","voters":7},{"year":2007,"party":"GPS/PES","voters":8},{"year":2007,"party":"SVP/UDC","voters":87},{"year":2007,"party":"GLP/PVL","voters":0},{"year":2007,"party":"CVP/PDC","voters":138},{"year":2007,"party":"BDP/PBD","voters":0},{"year":2011,"party":"CVP/PDC","voters":155},{"year":2011,"party":"GPS/PES","voters":7},{"year":2011,"party":"GLP/PVL","voters":5},{"year":2011,"party":"Other","voters":3},{"year":2011,"party":"SP/PS","voters":9},{"year":2011,"party":"BDP/PBD","voters":5},{"year":2011,"party":"FDP/PLR (PRD)","voters":52},{"year":2011,"party":"SVP/UDC","voters":90}],"building_investments_by_category":[{"year":1995,"category":"Bildung, Forschung","amount":2000000},{"year":1995,"category":"Gesundheit","amount":0},{"year":1995,"category":"Infrastruktur","amount":973000},{"year":1995,"category":"Freizeit, Kultur","amount":0},{"year":1995,"category":"Wohnen","amount":5392000},{"year":1995,"category":"Land- und Forstwirtschaft","amount":0},{"year":1995,"category":"Industrie, Gewerbe, Dienstleistungen","amount":0},{"year":1996,"category":"Bildung, Forschung","amount":200000},{"year":1996,"category":"Wohnen","amount":1616000},{"year":1996,"category":"Freizeit, Kultur","amount":0},{"year":1996,"category":"Gesundheit","amount":0},{"year":1996,"category":"Industrie, Gewerbe, Dienstleistungen","amount":0},{"year":1996,"category":"Infrastruktur","amount":158000},{"year":1996,"category":"Land- und Forstwirtschaft","amount":0},{"year":1997,"category":"Bildung, Forschung","amount":2000000},{"year":1997,"category":"Industrie, Gewerbe, Dienstleistungen","amount":479000},{"year":1997,"category":"Land- und Forstwirtschaft","amount":895000},{"year":1997,"category":"Infrastruktur","amount":969000},{"year":1997,"category":"Freizeit, Kultur","amount":0},{"year":1997,"category":"Gesundheit","amount":0},{"year":1997,"category":"Wohnen","amount":1910000},{"year":1998,"category":"Land- und Forstwirtschaft","amount":1255000},{"year":1998,"category":"Wohnen","amount":958000},{"year":1998,"category":"Freizeit, Kultur","amount":0},{"year":1998,"category":"Bildung, Forschung","amount":1500000},{"year":1998,"category":"Gesundheit","amount":0},{"year":1998,"category":"Industrie, Gewerbe, Dienstleistungen","amount":515000},{"year":1998,"category":"Infrastruktur","amount":3000},{"year":1999,"category":"Wohnen","amount":529000},{"year":1999,"category":"Infrastruktur","amount":194000},{"year":1999,"category":"Bildung, Forschung","amount":300000},{"year":1999,"category":"Industrie, Gewerbe, Dienstleistungen","amount":42000},{"year":1999,"category":"Freizeit, Kultur","amount":0},{"year":1999,"category":"Gesundheit","amount":0},{"year":1999,"category":"Land- und Forstwirtschaft","amount":1110000},{"year":2000,"category":"Freizeit, Kultur","amount":0},{"year":2000,"category":"Bildung, Forschung","amount":0},{"year":2000,"category":"Land- und Forstwirtschaft","amount":710000},{"year":2000,"category":"Gesundheit","amount":0},{"year":2000,"category":"Infrastruktur","amount":1000},{"year":2000,"category":"Industrie, Gewerbe, Dienstleistungen","amount":250000},{"year":2000,"category":"Wohnen","amount":840000},{"year":2001,"category":"Gesundheit","amount":0},{"year":2001,"category":"Freizeit, Kultur","amount":0},{"year":2001,"category":"Wohnen","amount":2070000},{"year":2001,"category":"Bildung, Forschung","amount":0},{"year":2001,"category":"Industrie, Gewerbe, Dienstleistungen","amount":175000},{"year":2001,"category":"Land- und Forstwirtschaft","amount":615000},{"year":2001,"category":"Infrastruktur","amount":0},{"year":2002,"category":"Bildung, Forschung","amount":0},{"year":2002,"category":"Land- und Forstwirtschaft","amount":495000},{"year":2002,"category":"Freizeit, Kultur","amount":0},{"year":2002,"category":"Infrastruktur","amount":0},{"year":2002,"category":"Gesundheit","amount":0},{"year":2002,"category":"Industrie, Gewerbe, Dienstleistungen","amount":110000},{"year":2002,"category":"Wohnen","amount":2006000},{"year":2003,"category":"Gesundheit","amount":0},{"year":2003,"category":"Bildung, Forschung","amount":0},{"year":2003,"category":"Freizeit, Kultur","amount":0},{"year":2003,"category":"Wohnen","amount":2969000},{"year":2003,"category":"Industrie, Gewerbe, Dienstleistungen","amount":170000},{"year":2003,"category":"Infrastruktur","amount":400000},{"year":2003,"category":"Land- und Forstwirtschaft","amount":365000},{"year":2004,"category":"Gesundheit","amount":0},{"year":2004,"category":"Industrie, Gewerbe, Dienstleistungen","amount":255000},{"year":2004,"category":"Freizeit, Kultur","amount":0},{"year":2004,"category":"Infrastruktur","amount":530000},{"year":2004,"category":"Bildung, Forschung","amount":0},{"year":2004,"category":"Land- und Forstwirtschaft","amount":1249000},{"year":2004,"category":"Wohnen","amount":2753000},{"year":2005,"category":"Bildung, Forschung","amount":0},{"year":2005,"category":"Infrastruktur","amount":100000},{"year":2005,"category":"Freizeit, Kultur","amount":0},{"year":2005,"category":"Industrie, Gewerbe, Dienstleistungen","amount":1000000},{"year":2005,"category":"Land- und Forstwirtschaft","amount":1360000},{"year":2005,"category":"Wohnen","amount":2287000},{"year":2005,"category":"Gesundheit","amount":0},{"year":2006,"category":"Infrastruktur","amount":202000},{"year":2006,"category":"Bildung, Forschung","amount":0},{"year":2006,"category":"Gesundheit","amount":0},{"year":2006,"category":"Industrie, Gewerbe, Dienstleistungen","amount":602000},{"year":2006,"category":"Wohnen","amount":1423000},{"year":2006,"category":"Freizeit, Kultur","amount":20000},{"year":2006,"category":"Land- und Forstwirtschaft","amount":235000},{"year":2007,"category":"Land- und Forstwirtschaft","amount":406000},{"year":2007,"category":"Industrie, Gewerbe, Dienstleistungen","amount":30000},{"year":2007,"category":"Freizeit, Kultur","amount":0},{"year":2007,"category":"Bildung, Forschung","amount":0},{"year":2007,"category":"Wohnen","amount":1566000},{"year":2007,"category":"Infrastruktur","amount":0},{"year":2007,"category":"Gesundheit","amount":0},{"year":2008,"category":"Gesundheit","amount":0},{"year":2008,"category":"Infrastruktur","amount":419000},{"year":2008,"category":"Bildung, Forschung","amount":0},{"year":2008,"category":"Wohnen","amount":3739000},{"year":2008,"category":"Land- und Forstwirtschaft","amount":181000},{"year":2008,"category":"Freizeit, Kultur","amount":0},{"year":2008,"category":"Industrie, Gewerbe, Dienstleistungen","amount":11000},{"year":2009,"category":"Infrastruktur","amount":242000},{"year":2009,"category":"Industrie, Gewerbe, Dienstleistungen","amount":394000},{"year":2009,"category":"Gesundheit","amount":0},{"year":2009,"category":"Bildung, Forschung","amount":20000},{"year":2009,"category":"Wohnen","amount":1942000},{"year":2009,"category":"Freizeit, Kultur","amount":2000},{"year":2009,"category":"Land- und Forstwirtschaft","amount":303000},{"year":2010,"category":"Freizeit, Kultur","amount":0},{"year":2010,"category":"Wohnen","amount":4751000},{"year":2010,"category":"Infrastruktur","amount":276000},{"year":2010,"category":"Land- und Forstwirtschaft","amount":67000},{"year":2010,"category":"Industrie, Gewerbe, Dienstleistungen","amount":1764000},{"year":2010,"category":"Bildung, Forschung","amount":0},{"year":2010,"category":"Gesundheit","amount":0},{"year":2011,"category":"Industrie, Gewerbe, Dienstleistungen","amount":925000},{"year":2011,"category":"Freizeit, Kultur","amount":0},{"year":2011,"category":"Bildung, Forschung","amount":0},{"year":2011,"category":"Infrastruktur","amount":176000},{"year":2011,"category":"Land- und Forstwirtschaft","amount":165000},{"year":2011,"category":"Gesundheit","amount":0},{"year":2011,"category":"Wohnen","amount":1462000},{"year":2012,"category":"Gesundheit","amount":0},{"year":2012,"category":"Bildung, Forschung","amount":0},{"year":2012,"category":"Land- und Forstwirtschaft","amount":303000},{"year":2012,"category":"Wohnen","amount":4401000},{"year":2012,"category":"Infrastruktur","amount":172000},{"year":2012,"category":"Industrie, Gewerbe, Dienstleistungen","amount":471000},{"year":2012,"category":"Freizeit, Kultur","amount":0}],"flats_by_rooms":[{"year":2009,"rooms":"5","flats":78},{"year":2009,"rooms":"4","flats":75},{"year":2009,"rooms":"2","flats":26},{"year":2009,"rooms":"1","flats":5},{"year":2009,"rooms":"6+","flats":86},{"year":2009,"rooms":"3","flats":57},{"year":2010,"rooms":"4","flats":80},{"year":2010,"rooms":"3","flats":57},{"year":2010,"rooms":"5","flats":79},{"year":2010,"rooms":"6+","flats":87},{"year":2010,"rooms":"1","flats":5},{"year":2010,"rooms":"2","flats":27},{"year":2011,"rooms":"1","flats":5},{"year":2011,"rooms":"2","flats":27},{"year":2011,"rooms":"3","flats":57},{"year":2011,"rooms":"4","flats":80},{"year":2011,"rooms":"6+","flats":87},{"year":2011,"rooms":"5","flats":81},{"year":2012,"rooms":"5","flats":85},{"year":2012,"rooms":"6+","flats":88},{"year":2012,"rooms":"4","flats":80},{"year":2012,"rooms":"1","flats":4},{"year":2012,"rooms":"2","flats":27},{"year":2012,"rooms":"3","flats":57},{"year":2013,"rooms":"5","flats":88},{"year":2013,"rooms":"4","flats":84},{"year":2013,"rooms":"3","flats":58},{"year":2013,"rooms":"6+","flats":91},{"year":2013,"rooms":"1","flats":3},{"year":2013,"rooms":"2","flats":27},{"year":2014,"rooms":"6+","flats":89},{"year":2014,"rooms":"2","flats":27},{"year":2014,"rooms":"3","flats":58},{"year":2014,"rooms":"5","flats":88},{"year":2014,"rooms":"1","flats":3},{"year":2014,"rooms":"4","flats":86}],"marriages":[{"year":1984,"origin_man":"Switzerland","origin_woman":"Switzerland","marriages":4},{"year":1984,"origin_man":"Foreign country","origin_woman":"Switzerland","marriages":0},{"year":1984,"origin_man":"Foreign country","origin_woman":"Foreign country","marriages":0},{"year":1984,"origin_man":"Switzerland","origin_woman":"Foreign country","marriages":0},{"year":1985,"origin_man":"Switzerland","origin_woman":"Foreign country","marriages":0},{"year":1985,"origin_man":"Foreign country","origin_woman":"Foreign country","marriages":0},{"year":1985,"origin_man":"Foreign country","origin_woman":"Switzerland","marriages":0},{"year":1985,"origin_man":"Switzerland","origin_woman":"Switzerland","marriages":3},{"year":1986,"origin_man":"Switzerland","origin_woman":"Foreign country","marriages":0},{"year":1986,"origin_man":"Foreign country","origin_woman":"Foreign country","marriages":0},{"year":1986,"origin_man":"Foreign country","origin_woman":"Switzerland","marriages":0},{"year":1986,"origin_man":"Switzerland","origin_woman":"Switzerland","marriages":2},{"year":1987,"origin_man":"Switzerland","origin_woman":"Foreign country","marriages":0},{"year":1987,"origin_man":"Foreign country","origin_woman":"Foreign country","marriages":0},{"year":1987,"origin_man":"Foreign country","origin_woman":"Switzerland","marriages":0},{"year":1987,"origin_man":"Switzerland","origin_woman":"Switzerland","marriages":8},{"year":1988,"origin_man":"Switzerland","origin_woman":"Foreign country","marriages":1},{"year":1988,"origin_man":"Foreign country","origin_woman":"Foreign country","marriages":0},{"year":1988,"origin_man":"Foreign country","origin_woman":"Switzerland","marriages":0},{"year":1988,"origin_man":"Switzerland","origin_woman":"Switzerland","marriages":8},{"year":1989,"origin_man":"Switzerland","origin_woman":"Foreign country","marriages":0},{"year":1989,"origin_man":"Foreign country","origin_woman":"Foreign country","marriages":0},{"year":1989,"origin_man":"Foreign country","origin_woman":"Switzerland","marriages":0},{"year":1989,"origin_man":"Switzerland","origin_woman":"Switzerland","marriages":4},{"year":1990,"origin_man":"Switzerland","origin_woman":"Foreign country","marriages":0},{"year":1990,"origin_man":"Foreign country","origin_woman":"Foreign country","marriages":0},{"year":1990,"origin_man":"Foreign country","origin_woman":"Switzerland","marriages":0},{"year":1990,"origin_man":"Switzerland","origin_woman":"Switzerland","marriages":7},{"year":1991,"origin_man":"Foreign country","origin_woman":"Switzerland","marriages":0},{"year":1991,"origin_man":"Foreign country","origin_woman":"Foreign country","marriages":0},{"year":1991,"origin_man":"Switzerland","origin_woman":"Foreign country","marriages":0},{"year":1991,"origin_man":"Switzerland","origin_woman":"Switzerland","marriages":6},{"year":1992,"origin_man":"Switzerland","origin_woman":"Switzerland","marriages":5},{"year":1992,"origin_man":"Foreign country","origin_woman":"Foreign country","marriages":0},{"year":1992,"origin_man":"Foreign country","origin_woman":"Switzerland","marriages":0},{"year":1992,"origin_man":"Switzerland","origin_woman":"Foreign country","marriages":0},{"year":1993,"origin_man":"Switzerland","origin_woman":"Foreign country","marriages":0},{"year":1993,"origin_man":"Foreign country","origin_woman":"Foreign country","marriages":0},{"year":1993,"origin_man":"Foreign country","origin_woman":"Switzerland","marriages":0},{"year":1993,"origin_man":"Switzerland","origin_woman":"Switzerland","marriages":6},{"year":1994,"origin_man":"Switzerland","origin_woman":"Foreign country","marriages":0},{"year":1994,"origin_man":"Foreign country","origin_woman":"Foreign country","marriages":1},{"year":1994,"origin_man":"Foreign country","origin_woman":"Switzerland","marriages":0},{"year":1994,"origin_man":"Switzerland","origin_woman":"Switzerland","marriages":4},{"year":1995,"origin_man":"Switzerland","origin_woman":"Foreign country","marriages":0},{"year":1995,"origin_man":"Foreign country","origin_woman":"Foreign country","marriages":0},{"year":1995,"origin_man":"Foreign country","origin_woman":"Switzerland","marriages":0},{"year":1995,"origin_man":"Switzerland","origin_woman":"Switzerland","marriages":5},{"year":1996,"origin_man":"Switzerland","origin_woman":"Foreign country","marriages":0},{"year":1996,"origin_man":"Foreign country","origin_woman":"Foreign country","marriages":0},{"year":1996,"origin_man":"Foreign country","origin_woman":"Switzerland","marriages":0},{"year":1996,"origin_man":"Switzerland","origin_woman":"Switzerland","marriages":4},{"year":1997,"origin_man":"Switzerland","origin_woman":"Foreign country","marriages":0},{"year":1997,"origin_man":"Foreign country","origin_woman":"Foreign country","marriages":0},{"year":1997,"origin_man":"Foreign country","origin_woman":"Switzerland","marriages":0},{"year":1997,"origin_man":"Switzerland","origin_woman":"Switzerland","marriages":1},{"year":1998,"origin_man":"Foreign country","origin_woman":"Switzerland","marriages":0},{"year":1998,"origin_man":"Foreign country","origin_woman":"Foreign country","marriages":0},{"year":1998,"origin_man":"Switzerland","origin_woman":"Switzerland","marriages":1},{"year":1998,"origin_man":"Switzerland","origin_woman":"Foreign country","marriages":0},{"year":1999,"origin_man":"Foreign country","origin_woman":"Switzerland","marriages":0},{"year":1999,"origin_man":"Switzerland","origin_woman":"Switzerland","marriages":2},{"year":1999,"origin_man":"Switzerland","origin_woman":"Foreign country","marriages":0},{"year":1999,"origin_man":"Foreign country","origin_woman":"Foreign country","marriages":0},{"year":2000,"origin_man":"Switzerland","origin_woman":"Switzerland","marriages":3},{"year":2000,"origin_man":"Foreign country","origin_woman":"Foreign country","marriages":0},{"year":2000,"origin_man":"Foreign country","origin_woman":"Switzerland","marriages":0},{"year":2000,"origin_man":"Switzerland","origin_woman":"Foreign country","marriages":0},{"year":2001,"origin_man":"Switzerland","origin_woman":"Foreign country","marriages":1},{"year":2001,"origin_man":"Foreign country","origin_woman":"Foreign country","marriages":0},{"year":2001,"origin_man":"Foreign country","origin_woman":"Switzerland","marriages":0},{"year":2001,"origin_man":"Switzerland","origin_woman":"Switzerland","marriages":2},{"year":2002,"origin_man":"Switzerland","origin_woman":"Foreign country","marriages":1},{"year":2002,"origin_man":"Foreign country","origin_woman":"Foreign country","marriages":0},{"year":2002,"origin_man":"Foreign country","origin_woman":"Switzerland","marriages":0},{"year":2002,"origin_man":"Switzerland","origin_woman":"Switzerland","marriages":2},{"year":2003,"origin_man":"Switzerland","origin_woman":"Foreign country","marriages":0},{"year":2003,"origin_man":"Foreign country","origin_woman":"Foreign country","marriages":0},{"year":2003,"origin_man":"Foreign country","origin_woman":"Switzerland","marriages":1},{"year":2003,"origin_man":"Switzerland","origin_woman":"Switzerland","marriages":3},{"year":2004,"origin_man":"Switzerland","origin_woman":"Foreign country","marriages":0},{"year":2004,"origin_man":"Foreign country","origin_woman":"Foreign country","marriages":0},{"year":2004,"origin_man":"Foreign country","origin_woman":"Switzerland","marriages":0},{"year":2004,"origin_man":"Switzerland","origin_woman":"Switzerland","marriages":3},{"year":2005,"origin_man":"Switzerland","origin_woman":"Foreign country","marriages":0},{"year":2005,"origin_man":"Foreign country","origin_woman":"Foreign country","marriages":0},{"year":2005,"origin_man":"Foreign country","origin_woman":"Switzerland","marriages":0},{"year":2005,"origin_man":"Switzerland","origin_woman":"Switzerland","marriages":2},{"year":2006,"origin_man":"Switzerland","origin_woman":"Foreign country","marriages":0},{"year":2006,"origin_man":"Foreign country","origin_woman":"Foreign country","marriages":0},{"year":2006,"origin_man":"Foreign country","origin_woman":"Switzerland","marriages":0},{"year":2006,"origin_man":"Switzerland","origin_woman":"Switzerland","marriages":2},{"year":2007,"origin_man":"Foreign country","origin_woman":"Switzerland","marriages":0},{"year":2007,"origin_man":"Foreign country","origin_woman":"Foreign country","marriages":0},{"year":2007,"origin_man":"Switzerland","origin_woman":"Foreign country","marriages":0},{"year":2007,"origin_man":"Switzerland","origin_woman":"Switzerland","marriages":2},{"year":2008,"origin_man":"Switzerland","origin_woman":"Switzerland","marriages":3},{"year":2008,"origin_man":"Foreign country","origin_woman":"Foreign country","marriages":0},{"year":2008,"origin_man":"Foreign country","origin_woman":"Switzerland","marriages":1},{"year":2008,"origin_man":"Switzerland","origin_woman":"Foreign country","marriages":0},{"year":2009,"origin_man":"Switzerland","origin_woman":"Foreign country","marriages":2},{"year":2009,"origin_man":"Foreign country","origin_woman":"Foreign country","marriages":0},{"year":2009,"origin_man":"Foreign country","origin_woman":"Switzerland","marriages":1},{"year":2009,"origin_man":"Switzerland","origin_woman":"Switzerland","marriages":5},{"year":2010,"origin_man":"Switzerland","origin_woman":"Foreign country","marriages":0},{"year":2010,"origin_man":"Foreign country","origin_woman":"Foreign country","marriages":0},{"year":2010,"origin_man":"Foreign country","origin_woman":"Switzerland","marriages":0},{"year":2010,"origin_man":"Switzerland","origin_woman":"Switzerland","marriages":4},{"year":2011,"origin_man":"Switzerland","origin_woman":"Foreign country","marriages":1},{"year":2011,"origin_man":"Foreign country","origin_woman":"Foreign country","marriages":1},{"year":2011,"origin_man":"Foreign country","origin_woman":"Switzerland","marriages":0},{"year":2011,"origin_man":"Switzerland","origin_woman":"Switzerland","marriages":5},{"year":2012,"origin_man":"Switzerland","origin_woman":"Foreign country","marriages":0},{"year":2012,"origin_man":"Foreign country","origin_woman":"Foreign country","marriages":0},{"year":2012,"origin_man":"Foreign country","origin_woman":"Switzerland","marriages":0},{"year":2012,"origin_man":"Switzerland","origin_woman":"Switzerland","marriages":2},{"year":2013,"origin_man":"Switzerland","origin_woman":"Foreign country","marriages":0},{"year":2013,"origin_man":"Foreign country","origin_woman":"Foreign country","marriages":0},{"year":2013,"origin_man":"Foreign country","origin_woman":"Switzerland","marriages":0},{"year":2013,"origin_man":"Switzerland","origin_woman":"Switzerland","marriages":3},{"year":2014,"origin_man":"Foreign country","origin_woman":"Switzerland","marriages":0},{"year":2014,"origin_man":"Foreign country","origin_woman":"Foreign country","marriages":0},{"year":2014,"origin_man":"Switzerland","origin_woman":"Switzerland","marriages":3},{"year":2014,"origin_man":"Switzerland","origin_woman":"Foreign country","marriages":0}],"divorces":[{"year":1984,"origin_man":"Switzerland","origin_woman":"Switzerland","divorces":0},{"year":1984,"origin_man":"Foreign country","origin_woman":"Foreign country","divorces":0},{"year":1984,"origin_man":"Foreign country","origin_woman":"Switzerland","divorces":0},{"year":1984,"origin_man":"Switzerland","origin_woman":"Foreign country","divorces":0},{"year":1985,"origin_man":"Switzerland","origin_woman":"Foreign country","divorces":0},{"year":1985,"origin_man":"Foreign country","origin_woman":"Foreign country","divorces":0},{"year":1985,"origin_man":"Foreign country","origin_woman":"Switzerland","divorces":0},{"year":1985,"origin_man":"Switzerland","origin_woman":"Switzerland","divorces":0},{"year":1986,"origin_man":"Switzerland","origin_woman":"Foreign country","divorces":0},{"year":1986,"origin_man":"Foreign country","origin_woman":"Switzerland","divorces":0},{"year":1986,"origin_man":"Foreign country","origin_woman":"Foreign country","divorces":0},{"year":1986,"origin_man":"Switzerland","origin_woman":"Switzerland","divorces":0},{"year":1987,"origin_man":"Switzerland","origin_woman":"Switzerland","divorces":0},{"year":1987,"origin_man":"Foreign country","origin_woman":"Switzerland","divorces":0},{"year":1987,"origin_man":"Foreign country","origin_woman":"Foreign country","divorces":0},{"year":1987,"origin_man":"Switzerland","origin_woman":"Foreign country","divorces":0},{"year":1988,"origin_man":"Switzerland","origin_woman":"Foreign country","divorces":0},{"year":1988,"origin_man":"Foreign country","origin_woman":"Switzerland","divorces":0},{"year":1988,"origin_man":"Foreign country","origin_woman":"Foreign country","divorces":0},{"year":1988,"origin_man":"Switzerland","origin_woman":"Switzerland","divorces":0},{"year":1989,"origin_man":"Switzerland","origin_woman":"Switzerland","divorces":0},{"year":1989,"origin_man":"Switzerland","origin_woman":"Foreign country","divorces":0},{"year":1989,"origin_man":"Foreign country","origin_woman":"Switzerland","divorces":0},{"year":1989,"origin_man":"Foreign country","origin_woman":"Foreign country","divorces":0},{"year":1990,"origin_man":"Foreign country","origin_woman":"Switzerland","divorces":0},{"year":1990,"origin_man":"Switzerland","origin_woman":"Foreign country","divorces":0},{"year":1990,"origin_man":"Foreign country","origin_woman":"Foreign country","divorces":0},{"year":1990,"origin_man":"Switzerland","origin_woman":"Switzerland","divorces":1},{"year":1991,"origin_man":"Foreign country","origin_woman":"Switzerland","divorces":0},{"year":1991,"origin_man":"Foreign country","origin_woman":"Foreign country","divorces":0},{"year":1991,"origin_man":"Switzerland","origin_woman":"Switzerland","divorces":1},{"year":1991,"origin_man":"Switzerland","origin_woman":"Foreign country","divorces":0},{"year":1992,"origin_man":"Foreign country","origin_woman":"Switzerland","divorces":0},{"year":1992,"origin_man":"Foreign country","origin_woman":"Foreign country","divorces":0},{"year":1992,"origin_man":"Switzerland","origin_woman":"Foreign country","divorces":0},{"year":1992,"origin_man":"Switzerland","origin_woman":"Switzerland","divorces":0},{"year":1993,"origin_man":"Foreign country","origin_woman":"Switzerland","divorces":0},{"year":1993,"origin_man":"Foreign country","origin_woman":"Foreign country","divorces":0},{"year":1993,"origin_man":"Switzerland","origin_woman":"Foreign country","divorces":0},{"year":1993,"origin_man":"Switzerland","origin_woman":"Switzerland","divorces":0},{"year":1994,"origin_man":"Foreign country","origin_woman":"Foreign country","divorces":0},{"year":1994,"origin_man":"Foreign country","origin_woman":"Switzerland","divorces":0},{"year":1994,"origin_man":"Switzerland","origin_woman":"Foreign country","divorces":0},{"year":1994,"origin_man":"Switzerland","origin_woman":"Switzerland","divorces":0},{"year":1995,"origin_man":"Switzerland","origin_woman":"Switzerland","divorces":0},{"year":1995,"origin_man":"Foreign country","origin_woman":"Foreign country","divorces":0},{"year":1995,"origin_man":"Foreign country","origin_woman":"Switzerland","divorces":0},{"year":1995,"origin_man":"Switzerland","origin_woman":"Foreign country","divorces":0},{"year":1996,"origin_man":"Switzerland","origin_woman":"Switzerland","divorces":1},{"year":1996,"origin_man":"Foreign country","origin_woman":"Switzerland","divorces":0},{"year":1996,"origin_man":"Foreign country","origin_woman":"Foreign country","divorces":0},{"year":1996,"origin_man":"Switzerland","origin_woman":"Foreign country","divorces":0},{"year":1997,"origin_man":"Switzerland","origin_woman":"Switzerland","divorces":0},{"year":1997,"origin_man":"Switzerland","origin_woman":"Foreign country","divorces":0},{"year":1997,"origin_man":"Foreign country","origin_woman":"Switzerland","divorces":0},{"year":1997,"origin_man":"Foreign country","origin_woman":"Foreign country","divorces":0},{"year":1998,"origin_man":"Foreign country","origin_woman":"Foreign country","divorces":0},{"year":1998,"origin_man":"Switzerland","origin_woman":"Switzerland","divorces":0},{"year":1998,"origin_man":"Switzerland","origin_woman":"Foreign country","divorces":0},{"year":1998,"origin_man":"Foreign country","origin_woman":"Switzerland","divorces":0},{"year":1999,"origin_man":"Switzerland","origin_woman":"Switzerland","divorces":0},{"year":1999,"origin_man":"Foreign country","origin_woman":"Foreign country","divorces":0},{"year":1999,"origin_man":"Foreign country","origin_woman":"Switzerland","divorces":0},{"year":1999,"origin_man":"Switzerland","origin_woman":"Foreign country","divorces":0},{"year":2000,"origin_man":"Switzerland","origin_woman":"Switzerland","divorces":0},{"year":2000,"origin_man":"Switzerland","origin_woman":"Foreign country","divorces":1},{"year":2000,"origin_man":"Foreign country","origin_woman":"Switzerland","divorces":0},{"year":2000,"origin_man":"Foreign country","origin_woman":"Foreign country","divorces":0},{"year":2001,"origin_man":"Foreign country","origin_woman":"Foreign country","divorces":0},{"year":2001,"origin_man":"Switzerland","origin_woman":"Switzerland","divorces":0},{"year":2001,"origin_man":"Switzerland","origin_woman":"Foreign country","divorces":0},{"year":2001,"origin_man":"Foreign country","origin_woman":"Switzerland","divorces":0},{"year":2002,"origin_man":"Switzerland","origin_woman":"Switzerland","divorces":0},{"year":2002,"origin_man":"Switzerland","origin_woman":"Foreign country","divorces":0},{"year":2002,"origin_man":"Foreign country","origin_woman":"Foreign country","divorces":0},{"year":2002,"origin_man":"Foreign country","origin_woman":"Switzerland","divorces":0},{"year":2003,"origin_man":"Switzerland","origin_woman":"Switzerland","divorces":1},{"year":2003,"origin_man":"Switzerland","origin_woman":"Foreign country","divorces":0},{"year":2003,"origin_man":"Foreign country","origin_woman":"Switzerland","divorces":0},{"year":2003,"origin_man":"Foreign country","origin_woman":"Foreign country","divorces":0},{"year":2004,"origin_man":"Foreign country","origin_woman":"Foreign country","divorces":0},{"year":2004,"origin_man":"Switzerland","origin_woman":"Foreign country","divorces":0},{"year":2004,"origin_man":"Foreign country","origin_woman":"Switzerland","divorces":0},{"year":2004,"origin_man":"Switzerland","origin_woman":"Switzerland","divorces":0},{"year":2005,"origin_man":"Switzerland","origin_woman":"Switzerland","divorces":1},{"year":2005,"origin_man":"Foreign country","origin_woman":"Switzerland","divorces":0},{"year":2005,"origin_man":"Foreign country","origin_woman":"Foreign country","divorces":0},{"year":2005,"origin_man":"Switzerland","origin_woman":"Foreign country","divorces":0},{"year":2006,"origin_man":"Foreign country","origin_woman":"Foreign country","divorces":0},{"year":2006,"origin_man":"Switzerland","origin_woman":"Switzerland","divorces":0},{"year":2006,"origin_man":"Switzerland","origin_woman":"Foreign country","divorces":0},{"year":2006,"origin_man":"Foreign country","origin_woman":"Switzerland","divorces":0},{"year":2007,"origin_man":"Foreign country","origin_woman":"Foreign country","divorces":0},{"year":2007,"origin_man":"Switzerland","origin_woman":"Foreign country","divorces":0},{"year":2007,"origin_man":"Foreign country","origin_woman":"Switzerland","divorces":0},{"year":2007,"origin_man":"Switzerland","origin_woman":"Switzerland","divorces":1},{"year":2008,"origin_man":"Switzerland","origin_woman":"Foreign country","divorces":0},{"year":2008,"origin_man":"Foreign country","origin_woman":"Foreign country","divorces":0},{"year":2008,"origin_man":"Foreign country","origin_woman":"Switzerland","divorces":0},{"year":2008,"origin_man":"Switzerland","origin_woman":"Switzerland","divorces":1},{"year":2009,"origin_man":"Switzerland","origin_woman":"Switzerland","divorces":1},{"year":2009,"origin_man":"Switzerland","origin_woman":"Foreign country","divorces":0},{"year":2009,"origin_man":"Foreign country","origin_woman":"Switzerland","divorces":0},{"year":2009,"origin_man":"Foreign country","origin_woman":"Foreign country","divorces":0},{"year":2010,"origin_man":"Foreign country","origin_woman":"Switzerland","divorces":0},{"year":2010,"origin_man":"Switzerland","origin_woman":"Switzerland","divorces":3},{"year":2010,"origin_man":"Switzerland","origin_woman":"Foreign country","divorces":0},{"year":2010,"origin_man":"Foreign country","origin_woman":"Foreign country","divorces":1},{"year":2011,"origin_man":"Switzerland","origin_woman":"Switzerland","divorces":1},{"year":2011,"origin_man":"Foreign country","origin_woman":"Foreign country","divorces":0},{"year":2011,"origin_man":"Foreign country","origin_woman":"Switzerland","divorces":0},{"year":2011,"origin_man":"Switzerland","origin_woman":"Foreign country","divorces":1},{"year":2012,"origin_man":"Foreign country","origin_woman":"Switzerland","divorces":0},{"year":2012,"origin_man":"Switzerland","origin_woman":"Foreign country","divorces":0},{"year":2012,"origin_man":"Switzerland","origin_woman":"Switzerland","divorces":0},{"year":2012,"origin_man":"Foreign country","origin_woman":"Foreign country","divorces":0},{"year":2013,"origin_man":"Switzerland","origin_woman":"Foreign country","divorces":0},{"year":2013,"origin_man":"Foreign country","origin_woman":"Switzerland","divorces":0},{"year":2013,"origin_man":"Switzerland","origin_woman":"Switzerland","divorces":2},{"year":2013,"origin_man":"Foreign country","origin_woman":"Foreign country","divorces":0},{"year":2014,"origin_man":"Switzerland","origin_woman":"Switzerland","divorces":0},{"year":2014,"origin_man":"Switzerland","origin_woman":"Foreign country","divorces":0},{"year":2014,"origin_man":"Foreign country","origin_woman":"Switzerland","divorces":0},{"year":2014,"origin_man":"Foreign country","origin_woman":"Foreign country","divorces":0}],"building_projects":[{"year":1995,"construction_type":"Tiefbau","work_type":"Neubau","amount":20000},{"year":1995,"construction_type":"Hochbau","work_type":"Neubau","amount":1642000},{"year":1995,"construction_type":"Tiefbau","work_type":"Umbau","amount":0},{"year":1995,"construction_type":"Hochbau","work_type":"Umbau","amount":2250000},{"year":1996,"construction_type":"Hochbau","work_type":"Umbau","amount":2000000},{"year":1996,"construction_type":"Hochbau","work_type":"Neubau","amount":3412000},{"year":1996,"construction_type":"Tiefbau","work_type":"Umbau","amount":0},{"year":1996,"construction_type":"Tiefbau","work_type":"Neubau","amount":150000},{"year":1997,"construction_type":"Tiefbau","work_type":"Umbau","amount":0},{"year":1997,"construction_type":"Tiefbau","work_type":"Neubau","amount":2000},{"year":1997,"construction_type":"Hochbau","work_type":"Umbau","amount":1633000},{"year":1997,"construction_type":"Hochbau","work_type":"Neubau","amount":767000},{"year":1998,"construction_type":"Hochbau","work_type":"Neubau","amount":737000},{"year":1998,"construction_type":"Tiefbau","work_type":"Umbau","amount":0},{"year":1998,"construction_type":"Tiefbau","work_type":"Neubau","amount":0},{"year":1998,"construction_type":"Hochbau","work_type":"Umbau","amount":500000},{"year":1999,"construction_type":"Hochbau","work_type":"Neubau","amount":660000},{"year":1999,"construction_type":"Hochbau","work_type":"Umbau","amount":140000},{"year":1999,"construction_type":"Tiefbau","work_type":"Neubau","amount":0},{"year":1999,"construction_type":"Tiefbau","work_type":"Umbau","amount":0},{"year":2000,"construction_type":"Hochbau","work_type":"Umbau","amount":270000},{"year":2000,"construction_type":"Tiefbau","work_type":"Umbau","amount":0},{"year":2000,"construction_type":"Tiefbau","work_type":"Neubau","amount":0},{"year":2000,"construction_type":"Hochbau","work_type":"Neubau","amount":620000},{"year":2001,"construction_type":"Hochbau","work_type":"Umbau","amount":118000},{"year":2001,"construction_type":"Hochbau","work_type":"Neubau","amount":1080000},{"year":2001,"construction_type":"Tiefbau","work_type":"Umbau","amount":0},{"year":2001,"construction_type":"Tiefbau","work_type":"Neubau","amount":0},{"year":2002,"construction_type":"Tiefbau","work_type":"Neubau","amount":0},{"year":2002,"construction_type":"Hochbau","work_type":"Umbau","amount":220000},{"year":2002,"construction_type":"Hochbau","work_type":"Neubau","amount":1050000},{"year":2002,"construction_type":"Tiefbau","work_type":"Umbau","amount":10000},{"year":2003,"construction_type":"Hochbau","work_type":"Umbau","amount":590000},{"year":2003,"construction_type":"Tiefbau","work_type":"Umbau","amount":0},{"year":2003,"construction_type":"Tiefbau","work_type":"Neubau","amount":0},{"year":2003,"construction_type":"Hochbau","work_type":"Neubau","amount":1155000},{"year":2004,"construction_type":"Hochbau","work_type":"Umbau","amount":185000},{"year":2004,"construction_type":"Tiefbau","work_type":"Umbau","amount":100000},{"year":2004,"construction_type":"Hochbau","work_type":"Neubau","amount":2135000},{"year":2004,"construction_type":"Tiefbau","work_type":"Neubau","amount":0},{"year":2005,"construction_type":"Hochbau","work_type":"Umbau","amount":289000},{"year":2005,"construction_type":"Tiefbau","work_type":"Neubau","amount":1000000},{"year":2005,"construction_type":"Hochbau","work_type":"Neubau","amount":1488000},{"year":2005,"construction_type":"Tiefbau","work_type":"Umbau","amount":0},{"year":2006,"construction_type":"Hochbau","work_type":"Neubau","amount":972000},{"year":2006,"construction_type":"Tiefbau","work_type":"Umbau","amount":98000},{"year":2006,"construction_type":"Tiefbau","work_type":"Neubau","amount":1000000},{"year":2006,"construction_type":"Hochbau","work_type":"Umbau","amount":230000},{"year":2007,"construction_type":"Tiefbau","work_type":"Neubau","amount":1135000},{"year":2007,"construction_type":"Tiefbau","work_type":"Umbau","amount":98000},{"year":2007,"construction_type":"Hochbau","work_type":"Neubau","amount":2659000},{"year":2007,"construction_type":"Hochbau","work_type":"Umbau","amount":590000},{"year":2008,"construction_type":"Tiefbau","work_type":"Neubau","amount":205000},{"year":2008,"construction_type":"Hochbau","work_type":"Umbau","amount":15000},{"year":2008,"construction_type":"Tiefbau","work_type":"Umbau","amount":0},{"year":2008,"construction_type":"Hochbau","work_type":"Neubau","amount":2152000},{"year":2009,"construction_type":"Hochbau","work_type":"Neubau","amount":5726000},{"year":2009,"construction_type":"Tiefbau","work_type":"Neubau","amount":50000},{"year":2009,"construction_type":"Tiefbau","work_type":"Umbau","amount":85000},{"year":2009,"construction_type":"Hochbau","work_type":"Umbau","amount":551000},{"year":2010,"construction_type":"Hochbau","work_type":"Neubau","amount":1478000},{"year":2010,"construction_type":"Hochbau","work_type":"Umbau","amount":319000},{"year":2010,"construction_type":"Tiefbau","work_type":"Neubau","amount":81000},{"year":2010,"construction_type":"Tiefbau","work_type":"Umbau","amount":14000},{"year":2011,"construction_type":"Tiefbau","work_type":"Umbau","amount":0},{"year":2011,"construction_type":"Tiefbau","work_type":"Neubau","amount":66000},{"year":2011,"construction_type":"Hochbau","work_type":"Neubau","amount":767000},{"year":2011,"construction_type":"Hochbau","work_type":"Umbau","amount":596000},{"year":2012,"construction_type":"Hochbau","work_type":"Umbau","amount":1165000},{"year":2012,"construction_type":"Tiefbau","work_type":"Neubau","amount":110000},{"year":2012,"construction_type":"Tiefbau","work_type":"Umbau","amount":0},{"year":2012,"construction_type":"Hochbau","work_type":"Neubau","amount":5626000}]}